MANIFEST.in
README.rst
setup.cfg
setup.py
bin/s3
src/s3/__init__.py
src/s3/auth.py
src/s3/d2x.py
src/s3/s3.py
src/s3/util.py
src/s3.egg-info/PKG-INFO
src/s3.egg-info/SOURCES.txt
src/s3.egg-info/dependency_links.txt
src/s3.egg-info/requires.txt
src/s3.egg-info/top_level.txt
test/test_s3.py