Metadata-Version: 1.1
Name: s3
Version: 2.0.0
Summary: Python module which connects to Amazon's S3 REST API
Home-page: https://bitbucket.org/prometheus/s3/
Author: Paul Wexler
Author-email: paul@prometheusresearch.com
License: MIT
Keywords: amazon,aws,s3,upload,download
Platform: Any
Classifier: Programming Language :: Python
Classifier: Intended Audience :: Developers
